<?xml version="1.0"?>
<data><user>Admin</user><processed>2020-03-27 15:24:44</processed><Asset_Number>68379</Asset_Number><Product_Name>Laptop</Product_Name><Technology>Notebook</Technology><Model>T440s (Notebook)</Model><Weight>123</Weight><Part_Number>123</Part_Number><Color>Gray</Color><OS_Label>Windows 7 Enterprise</OS_Label><Customer_Asset_Tag>Worn Asset Tag</Customer_Asset_Tag><Screen><Size>9.7"</Size><Resolution>1280 x 720</Resolution><Touchscreen>Yes</Touchscreen></Screen><Components><HD_Size>m.2 SSD</HD_Size><Memory_Slots>5</Memory_Slots><Max_Memory_Capacity>16GB</Max_Memory_Capacity><Optical_Drive>Ultrabay Battery</Optical_Drive><Graphics_Processor>AMD Radeon HD 6350</Graphics_Processor></Components><Peripherials><Battery_and_Power>Battery_Yes</Battery_and_Power><Battery_Condition>Moderate</Battery_Condition><Backlit_Keyboard>Yes</Backlit_Keyboard><Fingerprint_Scanner>Yes</Fingerprint_Scanner><Webcam>Yes</Webcam></Peripherials><Ports><RJ_45>Yes</RJ_45><USB_2_0_Ports>6</USB_2_0_Ports><USB_3_0_Ports>3</USB_3_0_Ports><USB_C_Ports>4</USB_C_Ports><SD_Card_Reader>Yes</SD_Card_Reader><Headphone_Jack>Yes</Headphone_Jack><Microphone_Jack>Yes</Microphone_Jack></Ports><Dimensions><Height>123</Height><Width>213</Width><Length>321</Length></Dimensions><Description><Additional>Cracked_Screen</Additional><Additional>Defective_Backlight</Additional><Additional>Case_Engraved</Additional><Additional>Security_Plate</Additional><Additional>Worn_COA</Additional><Additional>Broken_Port_(Power)</Additional><Additional>BIOS_Lock</Additional><Additional>Defective_Power_Supply_x_1</Additional><Additional>Will_Not_Power_On</Additional><Additional>LCD_Screen</Additional><Additional>Rubber_Feet</Additional><Screen>Cracked_Screen</Screen><Screen>Defective_Backlight</Screen><Case>Case_Engraved</Case><Case>Security_Plate</Case><Case>Worn_COA</Case><Input_Output>Broken_Port_(Power)</Input_Output><Functional>BIOS_Lock</Functional><Functional>Defective_Power_Supply_x_1</Functional><Functional>Will_Not_Power_On</Functional><Missing>LCD_Screen</Missing><Missing>Rubber_Feet</Missing></Description><Grade>C</Grade></data>
